nonebot_plugin_anymate/__init__.py
nonebot_plugin_anymate/api.py
nonebot_plugin_anymate/api_operate.py
nonebot_plugin_anymate/config.py
nonebot_plugin_anymate/sql_operate.py
nonebot_plugin_anymate/tools.py
nonebot_plugin_anymate/functions/__init__.py
nonebot_plugin_anymate/functions/check_in.py
nonebot_plugin_anymate/functions/functions.py
nonebot_plugin_anymate/functions/login.py
nonebot_plugin_anymate/functions/upvote.py
nonebot_plugin_anymate/utils/__init__.py
nonebot_plugin_anymate/utils/send_msg.py
nonebot_plugin_anymate/utils/simple_func.py
nonebot_plugin_anymate-1.5.8.0.dist-info/LICENSE
nonebot_plugin_anymate-1.5.8.0.dist-info/METADATA
nonebot_plugin_anymate-1.5.8.0.dist-info/WHEEL
nonebot_plugin_anymate-1.5.8.0.dist-info/top_level.txt
nonebot_plugin_anymate-1.5.8.0.dist-info/RECORD
