Metadata-Version: 2.1
Name: nonebot_plugin_anymate
Version: 1.5.8.0
Summary: QQ上使用的anymate网站小工具
Home-page: https://github.com/QuickLAW/nonebot-plugin-anymate
Author: QuickLAW
Author-email: yewillwork@outlook.com
License: BSD 3-Clause License
Platform: all
Classifier: Intended Audience :: Developers
Classifier: Operating System :: OS Independent
Classifier: Natural Language :: Chinese (Simplified)
Classifier: Programming Language :: Python :: 3.10
Classifier: Programming Language :: Python :: 3.11
Classifier: Topic :: Software Development :: Libraries
License-File: LICENSE
Requires-Dist: anyio
Requires-Dist: filetype
Requires-Dist: strenum
Requires-Dist: pytz
Requires-Dist: httpx
Requires-Dist: pydantic
Requires-Dist: nonebot-adapter-onebot
Requires-Dist: aiosqlite
Requires-Dist: nonebot-plugin-send-anything-anywhere
Requires-Dist: nonebot-plugin-apscheduler
Requires-Dist: nonebot2
